jupyterlab_swift/__init__.py
jupyterlab_swift/config.py
jupyterlab_swift/handler/__init__.py
jupyterlab_swift/handler/base.py
jupyterlab_swift/handler/config.py
jupyterlab_swift/handler/contents.py
jupyterlab_swift/handler/decorator.py
jupyterlab_swift/handler/exception.py
jupyterlab_swift/handler/meta.py
jupyterlab_swift-0.2.5.data/data/etc/jupyter/jupyter_notebook_config.d/jupyterlab_swift.json
jupyterlab_swift-0.2.5.dist-info/LICENSE
jupyterlab_swift-0.2.5.dist-info/METADATA
jupyterlab_swift-0.2.5.dist-info/WHEEL
jupyterlab_swift-0.2.5.dist-info/top_level.txt
jupyterlab_swift-0.2.5.dist-info/zip-safe
jupyterlab_swift-0.2.5.dist-info/RECORD
