Metadata-Version: 2.1
Name: jupyterlab-swift
Version: 0.2.5
Summary: A Jupyter Notebook server extension which acts a proxy for a Swift API.
Home-page: https://www.chameleoncloud.org
Author: University of Chicago
Author-email: dev@chameleoncloud.org
License: BSD
Keywords: jupyter,jupyterlab,openstack,swift
Platform: Linux
Platform: Mac OS X
Platform: Windows
Classifier: Intended Audience :: Developers
Classifier: Intended Audience :: System Administrators
Classifier: Intended Audience :: Science/Research
Classifier: License :: OSI Approved :: BSD License
Classifier: Programming Language :: Python
Classifier: Programming Language :: Python :: 3
Requires-Dist: notebook
